.DS_Store
OpenGoddard/OpenGoddard.py
OpenGoddard/__init__.py
OpenGoddard/optimize.py
OpenGoddard-1.1.0.dist-info/DESCRIPTION.rst
OpenGoddard-1.1.0.dist-info/METADATA
OpenGoddard-1.1.0.dist-info/RECORD
OpenGoddard-1.1.0.dist-info/WHEEL
OpenGoddard-1.1.0.dist-info/metadata.json
OpenGoddard-1.1.0.dist-info/top_level.txt
