Metadata-Version: 2.0
Name: OpenGoddard
Version: 1.1.0
Summary: Optimal Trajectories module with PseudoSpectral Method
Home-page: https://github.com/istellartech/OpenGoddard
Author: Interstellar Technologies Inc.
Author-email: hoge@google.com
License: MIT
Keywords: optimization trajectory optimal control aerospace pseudospectral_method
Platform: UNKNOWN
Classifier: Development Status :: 4 - Beta
Classifier: Intended Audience :: Developers
Classifier: Intended Audience :: Science/Research
Classifier: Intended Audience :: Education
Classifier: Topic :: Scientific/Engineering
Classifier: Topic :: Scientific/Engineering :: Mathematics
Classifier: Topic :: Scientific/Engineering :: Physics
Classifier: License :: OSI Approved :: MIT License
Classifier: Programming Language :: Python :: 3
Classifier: Programming Language :: Python :: 3.3
Classifier: Programming Language :: Python :: 3.4
Classifier: Programming Language :: Python :: 3.5
Requires-Dist: matplotlib (>=2.0)
Requires-Dist: numpy (>=1.11)
Requires-Dist: scipy (>=0.18)
